PyTextProMax/__init__.py
PyTextProMax-2.5.dist-info/LICENSE
PyTextProMax-2.5.dist-info/METADATA
PyTextProMax-2.5.dist-info/WHEEL
PyTextProMax-2.5.dist-info/top_level.txt
PyTextProMax-2.5.dist-info/RECORD
