Metadata-Version: 2.1
Name: PyTextProMax
Version: 2.5
Summary: A simple but useful python library.
Author-email: Cittidabozo <diabetolover@gmail.com>
Project-URL: Homepage, https://github.com/CittiTheBozo/PyTextProMax
Project-URL: Bug Tracker, https://github.com/CittiTheBozo/PyTextProMax/issues
Classifier: Programming Language :: Python :: 3.11
Classifier: License :: OSI Approved :: MIT License
Classifier: Operating System :: OS Independent
Requires-Python: >=3.11
License-File: LICENSE
